abstracttoolforge/__init__.py
abstracttoolforge-0.0.1.dist-info/licenses/LICENSE
abstracttoolforge-0.0.1.dist-info/METADATA
abstracttoolforge-0.0.1.dist-info/WHEEL
abstracttoolforge-0.0.1.dist-info/top_level.txt
abstracttoolforge-0.0.1.dist-info/RECORD
