Metadata-Version: 2.4
Name: AbstractToolForge
Version: 0.0.1
Summary: A framework to enable Agentic AI to create and update tools when needed, while maintaining reproducibility of actions through versioning.
Author-email: AbstractToolForge Team <contact@abstracttoolforge.org>
Maintainer-email: AbstractToolForge Team <contact@abstracttoolforge.org>
License: MIT License
Project-URL: Homepage, https://github.com/abstracttoolforge/AbstractToolForge
Project-URL: Documentation, https://abstracttoolforge.readthedocs.io/
Project-URL: Repository, https://github.com/abstracttoolforge/AbstractToolForge
Project-URL: Bug Tracker, https://github.com/abstracttoolforge/AbstractToolForge/issues
Keywords: agentic-ai,tools,framework,versioning,reproducibility,ai-agents
Classifier: Development Status :: 2 - Pre-Alpha
Classifier: Intended Audience :: Developers
Classifier: Intended Audience :: Science/Research
Classifier: License :: OSI Approved :: MIT License
Classifier: Operating System :: OS Independent
Classifier: Programming Language :: Python :: 3
Classifier: Programming Language :: Python :: 3.8
Classifier: Programming Language :: Python :: 3.9
Classifier: Programming Language :: Python :: 3.10
Classifier: Programming Language :: Python :: 3.11
Classifier: Programming Language :: Python :: 3.12
Classifier: Topic :: Software Development :: Libraries :: Python Modules
Classifier: Topic :: Scientific/Engineering :: Artificial Intelligence
Requires-Python: >=3.8
License-File: LICENSE
Provides-Extra: dev
Requires-Dist: pytest>=6.0; extra == "dev"
Requires-Dist: black; extra == "dev"
Requires-Dist: flake8; extra == "dev"
Requires-Dist: mypy; extra == "dev"
Dynamic: license-file
